synthoor/__init__.py
synthoor/config.py
synthoor/envelope.py
synthoor/filters.py
synthoor/oscillator.py
synthoor/player.py
synthoor/sound.py
synthoor-1.0.1.dist-info/METADATA
synthoor-1.0.1.dist-info/WHEEL
synthoor-1.0.1.dist-info/top_level.txt
synthoor-1.0.1.dist-info/RECORD
